package test;

public class TestStudentDaoImpl
{
  /* Error */
  @org.junit.Test
  public void teseFindNearTest()
    throws java.text.ParseException
  {
    // Byte code:
    //   0: new 20	com/hp/dao/impl/StudentDaoImpl
    //   3: dup
    //   4: invokespecial 22	com/hp/dao/impl/StudentDaoImpl:<init>	()V
    //   7: astore_1
    //   8: new 23	com/hp/bean/Student
    //   11: dup
    //   12: invokespecial 25	com/hp/bean/Student:<init>	()V
    //   15: astore_2
    //   16: ldc 26
    //   18: istore_3
    //   19: aload_2
    //   20: iload_3
    //   21: invokevirtual 27	com/hp/bean/Student:setStu_id	(I)V
    //   24: aload_2
    //   25: ldc 31
    //   27: invokevirtual 33	com/hp/bean/Student:setStu_name	(Ljava/lang/String;)V
    //   30: aload_2
    //   31: ldc 37
    //   33: invokevirtual 39	com/hp/bean/Student:setStu_password	(Ljava/lang/String;)V
    //   36: aload_2
    //   37: ldc 42
    //   39: invokevirtual 43	com/hp/bean/Student:setCla_id	(I)V
    //   42: aload_2
    //   43: iconst_2
    //   44: invokevirtual 46	com/hp/bean/Student:setDep_id	(I)V
    //   47: aload_2
    //   48: ldc 49
    //   50: invokevirtual 51	com/hp/bean/Student:setStu_sex	(Ljava/lang/String;)V
    //   53: ldc 54
    //   55: astore 4
    //   57: new 56	java/text/SimpleDateFormat
    //   60: dup
    //   61: ldc 58
    //   63: invokespecial 60	java/text/SimpleDateFormat:<init>	(Ljava/lang/String;)V
    //   66: astore 5
    //   68: aload 5
    //   70: aload 4
    //   72: invokevirtual 62	java/text/SimpleDateFormat:parse	(Ljava/lang/String;)Ljava/util/Date;
    //   75: astore 6
    //   77: aload_2
    //   78: aload 6
    //   80: invokevirtual 66	com/hp/bean/Student:setStu_born	(Ljava/util/Date;)V
    //   83: aconst_null
    //   84: astore 7
    //   86: invokestatic 70	com/hp/util/MySessionFactory:getSessionFactory	()Lorg/hibernate/SessionFactory;
    //   89: invokeinterface 76 1 0
    //   94: astore 8
    //   96: aload 8
    //   98: invokeinterface 82 1 0
    //   103: astore 7
    //   105: aload 8
    //   107: aload_2
    //   108: invokeinterface 88 2 0
    //   113: aload 7
    //   115: invokeinterface 92 1 0
    //   120: goto +34 -> 154
    //   123: astore 8
    //   125: aload 8
    //   127: invokevirtual 97	java/lang/Exception:printStackTrace	()V
    //   130: aload 7
    //   132: ifnull +30 -> 162
    //   135: aconst_null
    //   136: astore 7
    //   138: goto +24 -> 162
    //   141: astore 9
    //   143: aload 7
    //   145: ifnull +6 -> 151
    //   148: aconst_null
    //   149: astore 7
    //   151: aload 9
    //   153: athrow
    //   154: aload 7
    //   156: ifnull +6 -> 162
    //   159: aconst_null
    //   160: astore 7
    //   162: return
    // Line number table:
    //   Java source line #26	-> byte code offset #0
    //   Java source line #27	-> byte code offset #8
    //   Java source line #28	-> byte code offset #16
    //   Java source line #30	-> byte code offset #19
    //   Java source line #31	-> byte code offset #24
    //   Java source line #32	-> byte code offset #30
    //   Java source line #33	-> byte code offset #36
    //   Java source line #34	-> byte code offset #42
    //   Java source line #35	-> byte code offset #47
    //   Java source line #36	-> byte code offset #53
    //   Java source line #37	-> byte code offset #57
    //   Java source line #38	-> byte code offset #68
    //   Java source line #39	-> byte code offset #77
    //   Java source line #48	-> byte code offset #83
    //   Java source line #50	-> byte code offset #86
    //   Java source line #51	-> byte code offset #96
    //   Java source line #52	-> byte code offset #105
    //   Java source line #53	-> byte code offset #113
    //   Java source line #55	-> byte code offset #123
    //   Java source line #56	-> byte code offset #125
    //   Java source line #58	-> byte code offset #130
    //   Java source line #59	-> byte code offset #135
    //   Java source line #57	-> byte code offset #141
    //   Java source line #58	-> byte code offset #143
    //   Java source line #59	-> byte code offset #148
    //   Java source line #61	-> byte code offset #151
    //   Java source line #58	-> byte code offset #154
    //   Java source line #59	-> byte code offset #159
    //   Java source line #63	-> byte code offset #162
    // Local variable table:
    //   start	length	slot	name	signature
    //   0	163	0	this	TestStudentDaoImpl
    //   7	2	1	stuDao	com.hp.dao.StudentDao
    //   15	93	2	stu	com.hp.bean.Student
    //   18	3	3	id	int
    //   55	16	4	born	String
    //   66	3	5	formatter	java.text.SimpleDateFormat
    //   75	4	6	date	java.util.Date
    //   84	77	7	tx	org.hibernate.Transaction
    //   94	12	8	session	org.hibernate.Session
    //   123	3	8	ex	Exception
    //   141	11	9	localObject	Object
    // Exception table:
    //   from	to	target	type
    //   86	120	123	java/lang/Exception
    //   86	130	141	finally
  }
}
